Workbook

Sheet Inventario
A1: Código | B1: Categoría | C1: Nombre del Producto | D1: Especificación Técnica / Presentación | E1: Rendimiento (M2/Unid) | F1: Precio Unitario (USD) | Z1: Ref_Metodos
A2: GRA-010 | B2: Grama Sintética | C2: Grama Artificial 10mm | D2: Fibra de polipropileno, tráfico ligero, ancho 2m | E2: 1.00 | F2: 7 | Z2: Efectivo (Divisas)
A3: GRA-020 | B3: Grama Sintética | C3: Grama Artificial 20mm | D3: Alta densidad, protección UV, ancho 2m | E3: 1.00 | F3: 9 | Z3: Transferencia / Pago Móvil
A4: GRA-030 | B4: Grama Sintética | C4: Grama Artificial 30mm | D4: Aspecto natural, tráfico medio/alto, ancho 2m | E4: 1.00 | F4: 11 | Z4: Zelle / Binance
A5: GRA-040 | B5: Grama Sintética | C5: Grama Artificial 40mm | D5: Premium ultra suave, tráfico alto, ancho 2m | E5: 1.00 | F5: 13
A6: VIN-ROL | B6: Revestimiento Piso | C6: Piso Vinil Royal | D6: Línea Cemento / Instalación con Pegamento | E6: 1.00 | F6: 10.5
A7: VIN-SPC | B7: Revestimiento Piso | C7: Piso Vinil SPC CLICK | D7: Sistema Click 4.2mm / Rígido e impermeable | E7: 2.20 | F7: 15
A8: VIN-3MM | B8: Revestimiento Piso | C8: Piso de Vinil 3mm | D8: Tráfico Comercial Elegante / Texturizado | E8: 3.34 | F8: 18
A9: PEG-A21 | B9: Pegamento | C9: Pega Acrílica Premium | D9: Cuñete 21 Litros / Para pisos de vinil | E9: 85.00 | F9: 178
A10: PEG-A10 | B10: Pegamento | C10: Pega Acrílica Estándar | D10: Cuñete 10 Litros / Para pisos de vinil | E10: 40.00 | F10: 95
A11: PEG-CUN | B11: Pegamento | C11: Cuñete de Pegamento | D11: 15.14 L / Alto agarre inicial | E11: 60.00 | F11: 280
A12: FOL-50X | B12: Jardín Vertical | C12: Follaje Artificial 50x50 | D12: Paneles ensamblables, interior/exterior | E12: 0.25 | F12: 9
A13: FOL-1M1 | B13: Jardín Vertical | C13: Follaje Artificial 3D | D13: 1m x 1m / Alta densidad realista | E13: 1.00 | F13: 15
A14: ENR-ART | B14: Jardín Vertical | C14: Enredadera Artificial | D14: Paquete 12 unidades de 2 metros c/u | E14: N/A | F14: 6
A15: WAL-PVC | B15: Revestimiento Pared | C15: Wall Panel PVC | D15: Ancho 15.5cm x Largo 2.90m | E15: 0.45 | F15: 10.5
A16: WAL-SLM | B16: Revestimiento Pared | C16: Wall Panel PVC SLIM | D16: Ancho 12cm x Largo 2.90m / Acanalado fino | E16: 0.34 | F16: 15.5
... A20: PEG-CCQ | B20: Pegamento | C20: Cemento de Contacto | D20: Envase 1/4 Galón / Uso general | E20: N/A | F20: 11

Sheet Presupuesto
B2: SUMINISTROS DECO ROYAL C.A. | G2: PRESUPUESTO | H2: N° _________
B3: RIF: J-50211718-0 | Sistema de Ventas Automatizado
B5: Razón Social / Nombre: | F5: Teléfono:
B6: RIF / C.I.: | F6: E-mail:
B7: Fecha Emisión: | C7: =TODAY() | F7: Dirección:
A10: Código | B10: Categoría | C10: Nombre del Producto | D10: Detalle / Especificación | E10: Cajas/Unid. | F10: M2 Totales | G10: Precio Unit. | H10: Total Item
B11: =IF(ISBLANK(A11), "", _xlfn.XLOOKUP(A11, Inventario!$A$2:$A$100, Inventario!$B$2:$B$100, "")) | C11: =IF(ISBLANK(A11), "", _xlfn.XLOOKUP(A11, Inventario!$A$2:$A$100, Inventario!$C$2:$C$100, "")) | D11: =IF(ISBLANK(A11), "", _xlfn.XLOOKUP(A11, Inventario!$A$2:$A$100, Inventario!$D$2:$D$100, "")) | G11: =IF(ISBLANK(A11), "", _xlfn.XLOOKUP(A11, Inventario!$A$2:$A$100, Inventario!$F$2:$F$100, "")) | H11: =IF(ISBLANK(A11), "", IF(F11>0, F11, E11) * G11)
B12: =IF(ISBLANK(A12), "", _xlfn.XLOOKUP(A12, Inventario!$A$2:$A$100, Inventario!$B$2:$B$100, "")) | C12: =IF(ISBLANK(A12), "", _xlfn.XLOOKUP(A12, Inventario!$A$2:$A$100, Inventario!$C$2:$C$100, "")) | D12: =IF(ISBLANK(A12), "", _xlfn.XLOOKUP(A12, Inventario!$A$2:$A$100, Inventario!$D$2:$D$100, "")) | G12: =IF(ISBLANK(A12), "", _xlfn.XLOOKUP(A12, Inventario!$A$2:$A$100, Inventario!$F$2:$F$100, "")) | H12: =IF(ISBLANK(A12), "", IF(F12>0, F12, E12) * G12)
B13: =IF(ISBLANK(A13), "", _xlfn.XLOOKUP(A13, Inventario!$A$2:$A$100, Inventario!$B$2:$B$100, "")) | C13: =IF(ISBLANK(A13), "", _xlfn.XLOOKUP(A13, Inventario!$A$2:$A$100, Inventario!$C$2:$C$100, "")) | D13: =IF(ISBLANK(A13), "", _xlfn.XLOOKUP(A13, Inventario!$A$2:$A$100, Inventario!$D$2:$D$100, "")) | G13: =IF(ISBLANK(A13), "", _xlfn.XLOOKUP(A13, Inventario!$A$2:$A$100, Inventario!$F$2:$F$100, "")) | H13: =IF(ISBLANK(A13), "", IF(F13>0, F13, E13) * G13)
B14: =IF(ISBLANK(A14), "", _xlfn.XLOOKUP(A14, Inventario!$A$2:$A$100, Inventario!$B$2:$B$100, "")) | C14: =IF(ISBLANK(A14), "", _xlfn.XLOOKUP(A14, Inventario!$A$2:$A$100, Inventario!$C$2:$C$100, "")) | D14: =IF(ISBLANK(A14), "", _xlfn.XLOOKUP(A14, Inventario!$A$2:$A$100, Inventario!$D$2:$D$100, "")) | G14: =IF(ISBLANK(A14), "", _xlfn.XLOOKUP(A14, Inventario!$A$2:$A$100, Inventario!$F$2:$F$100, "")) | H14: =IF(ISBLANK(A14), "", IF(F14>0, F14, E14) * G14)
B15: =IF(ISBLANK(A15), "", _xlfn.XLOOKUP(A15, Inventario!$A$2:$A$100, Inventario!$B$2:$B$100, "")) | C15: =IF(ISBLANK(A15), "", _xlfn.XLOOKUP(A15, Inventario!$A$2:$A$100, Inventario!$C$2:$C$100, "")) | D15: =IF(ISBLANK(A15), "", _xlfn.XLOOKUP(A15, Inventario!$A$2:$A$100, Inventario!$D$2:$D$100, "")) | G15: =IF(ISBLANK(A15), "", _xlfn.XLOOKUP(A15, Inventario!$A$2:$A$100, Inventario!$F$2:$F$100, "")) | H15: =IF(ISBLANK(A15), "", IF(F15>0, F15, E15) * G15)
B16: =IF(ISBLANK(A16), "", _xlfn.XLOOKUP(A16, Inventario!$A$2:$A$100, Inventario!$B$2:$B$100, "")) | C16: =IF(ISBLANK(A16), "", _xlfn.XLOOKUP(A16, Inventario!$A$2:$A$100, Inventario!$C$2:$C$100, "")) | D16: =IF(ISBLANK(A16), "", _xlfn.XLOOKUP(A16, Inventario!$A$2:$A$100, Inventario!$D$2:$D$100, "")) | G16: =IF(ISBLANK(A16), "", _xlfn.XLOOKUP(A16, Inventario!$A$2:$A$100, Inventario!$F$2:$F$100, "")) | H16: =IF(ISBLANK(A16), "", IF(F16>0, F16, E16) * G16)
B17: =IF(ISBLANK(A17), "", _xlfn.XLOOKUP(A17, Inventario!$A$2:$A$100, Inventario!$B$2:$B$100, "")) | C17: =IF(ISBLANK(A17), "", _xlfn.XLOOKUP(A17, Inventario!$A$2:$A$100, Inventario!$C$2:$C$100, "")) | D17: =IF(ISBLANK(A17), "", _xlfn.XLOOKUP(A17, Inventario!$A$2:$A$100, Inventario!$D$2:$D$100, "")) | G17: =IF(ISBLANK(A17), "", _xlfn.XLOOKUP(A17, Inventario!$A$2:$A$100, Inventario!$F$2:$F$100, "")) | H17: =IF(ISBLANK(A17), "", IF(F17>0, F17, E17) * G17)
B18: =IF(ISBLANK(A18), "", _xlfn.XLOOKUP(A18, Inventario!$A$2:$A$100, Inventario!$B$2:$B$100, "")) | C18: =IF(ISBLANK(A18), "", _xlfn.XLOOKUP(A18, Inventario!$A$2:$A$100, Inventario!$C$2:$C$100, "")) | D18: =IF(ISBLANK(A18), "", _xlfn.XLOOKUP(A18, Inventario!$A$2:$A$100, Inventario!$D$2:$D$100, "")) | G18: =IF(ISBLANK(A18), "", _xlfn.XLOOKUP(A18, Inventario!$A$2:$A$100, Inventario!$F$2:$F$100, "")) | H18: =IF(ISBLANK(A18), "", IF(F18>0, F18, E18) * G18)
B19: =IF(ISBLANK(A19), "", _xlfn.XLOOKUP(A19, Inventario!$A$2:$A$100, Inventario!$B$2:$B$100, "")) | C19: =IF(ISBLANK(A19), "", _xlfn.XLOOKUP(A19, Inventario!$A$2:$A$100, Inventario!$C$2:$C$100, "")) | D19: =IF(ISBLANK(A19), "", _xlfn.XLOOKUP(A19, Inventario!$A$2:$A$100, Inventario!$D$2:$D$100, "")) | G19: =IF(ISBLANK(A19), "", _xlfn.XLOOKUP(A19, Inventario!$A$2:$A$100, Inventario!$F$2:$F$100, "")) | H19: =IF(ISBLANK(A19), "", IF(F19>0, F19, E19) * G19)
B20: =IF(ISBLANK(A20), "", _xlfn.XLOOKUP(A20, Inventario!$A$2:$A$100, Inventario!$B$2:$B$100, "")) | C20: =IF(ISBLANK(A20), "", _xlfn.XLOOKUP(A20, Inventario!$A$2:$A$100, Inventario!$C$2:$C$100, "")) | D20: =IF(ISBLANK(A20), "", _xlfn.XLOOKUP(A20, Inventario!$A$2:$A$100, Inventario!$D$2:$D$100, "")) | G20: =IF(ISBLANK(A20), "", _xlfn.XLOOKUP(A20, Inventario!$A$2:$A$100, Inventario!$F$2:$F$100, "")) | H20: =IF(ISBLANK(A20), "", IF(F20>0, F20, E20) * G20)
B21: =IF(ISBLANK(A21), "", _xlfn.XLOOKUP(A21, Inventario!$A$2:$A$100, Inventario!$B$2:$B$100, "")) | C21: =IF(ISBLANK(A21), "", _xlfn.XLOOKUP(A21, Inventario!$A$2:$A$100, Inventario!$C$2:$C$100, "")) | D21: =IF(ISBLANK(A21), "", _xlfn.XLOOKUP(A21, Inventario!$A$2:$A$100, Inventario!$D$2:$D$100, "")) | G21: =IF(ISBLANK(A21), "", _xlfn.XLOOKUP(A21, Inventario!$A$2:$A$100, Inventario!$F$2:$F$100, "")) | H21: =IF(ISBLANK(A21), "", IF(F21>0, F21, E21) * G21)
B22: =IF(ISBLANK(A22), "", _xlfn.XLOOKUP(A22, Inventario!$A$2:$A$100, Inventario!$B$2:$B$100, "")) | C22: =IF(ISBLANK(A22), "", _xlfn.XLOOKUP(A22, Inventario!$A$2:$A$100, Inventario!$C$2:$C$100, "")) | D22: =IF(ISBLANK(A22), "", _xlfn.XLOOKUP(A22, Inventario!$A$2:$A$100, Inventario!$D$2:$D$100, "")) | G22: =IF(ISBLANK(A22), "", _xlfn.XLOOKUP(A22, Inventario!$A$2:$A$100, Inventario!$F$2:$F$100, "")) | H22: =IF(ISBLANK(A22), "", IF(F22>0, F22, E22) * G22)
... B25: =IF(ISBLANK(A25), "", _xlfn.XLOOKUP(A25, Inventario!$A$2:$A$100, Inventario!$B$2:$B$100, "")) | C25: =IF(ISBLANK(A25), "", _xlfn.XLOOKUP(A25, Inventario!$A$2:$A$100, Inventario!$C$2:$C$100, "")) | D25: =IF(ISBLANK(A25), "", _xlfn.XLOOKUP(A25, Inventario!$A$2:$A$100, Inventario!$D$2:$D$100, "")) | G25: =IF(ISBLANK(A25), "", _xlfn.XLOOKUP(A25, Inventario!$A$2:$A$100, Inventario!$F$2:$F$100, "")) | H25: =IF(ISBLANK(A25), "", IF(F25>0, F25, E25) * G25)
G26: SUB-TOTAL | H26: =SUM(H11:H25)
G27: IVA (16%) | H27: =H26*0.16
G28: TOTAL GENERAL | H28: =H26+H27
A30: TÉRMINOS Y CONDICIONES: | E30: MÉTODO DE PAGO: | F30: Seleccione Método 🔽
A31: 1. Presupuesto válido por 15 días a partir de la fecha de emisión. | E31: =IF($F$30="Efectivo (Divisas)", "[ ✔ ] Efectivo (Divisas)", "[ ] Efectivo (Divisas)")
A32: 2. Los precios están sujetos a cambio sin previo aviso. | E32: =IF($F$30="Transferencia / Pago Móvil", "[ ✔ ] Transferencia / Pago Móvil", "[ ] Transferencia / Pago Móvil")
A33: 3. Las devoluciones de material sobrante aplican recargos. | E33: =IF($F$30="Zelle / Binance", "[ ✔ ] Zelle / Binance", "[ ] Zelle / Binance")
B37: ____________________________ | F37: ____________________________
B38: Firma del Asesor | F38: Firma del Cliente (Aceptación)
